nac_pusher/__init__.py
nac_pusher/feishu.py
nac_pusher-0.1.3.dist-info/licenses/LICENSE
nac_pusher-0.1.3.dist-info/METADATA
nac_pusher-0.1.3.dist-info/WHEEL
nac_pusher-0.1.3.dist-info/top_level.txt
nac_pusher-0.1.3.dist-info/RECORD
