Metadata-Version: 2.4
Name: nac-pusher
Version: 0.1.3
Summary: A Python package for pushing messages to Feishu (Lark)
Home-page: https://github.com/yourusername/nac-pusher
Author: Necoarc
Author-email: Necoarc <3306601284@qq.com>
Project-URL: Homepage, https://github.com/yourusername/nac-pusher
Project-URL: Repository, https://github.com/yourusername/nac-pusher
Classifier: Development Status :: 3 - Alpha
Classifier: Intended Audience :: Developers
Classifier: License :: OSI Approved :: MIT License
Classifier: Programming Language :: Python :: 3
Classifier: Programming Language :: Python :: 3.11
Requires-Python: >=3.7
License-File: LICENSE
Requires-Dist: lark-oapi>=1.4.22
Dynamic: author
Dynamic: home-page
Dynamic: license-file
Dynamic: requires-python
